wrapcord/__init__.py
wrapcord/discord.py
wrapcord/webhook.py
wrapcord-0.1.3.dist-info/LICENSE
wrapcord-0.1.3.dist-info/METADATA
wrapcord-0.1.3.dist-info/WHEEL
wrapcord-0.1.3.dist-info/top_level.txt
wrapcord-0.1.3.dist-info/RECORD
