Metadata-Version: 2.1
Name: wrapcord
Version: 0.1.3
Summary: Helpful tools for Discord.
Home-page: https://github.com/Somespi/Wrapcord/
Author: Someone
Author-email: 
License: MIT
Keywords: API,wrapper,discord,tools,wrapcord
License-File: LICENSE
Requires-Dist: requests
